fastclient/__init__.py
fastclient/cli.py
fastclient/const/__init__.py
fastclient/const/extentions.py
fastclient/const/files.py
fastclient/const/http.py
fastclient/const/regexp.py
fastclient/const/specification.py
fastclient/const/symbols.py
fastclient/const/syntax.py
fastclient/const/templates.py
fastclient/enums/__init__.py
fastclient/enums/http.py
fastclient/enums/python.py
fastclient/enums/specification.py
fastclient/enums/typing.py
fastclient/mappers/__init__.py
fastclient/mappers/python.py
fastclient/mappers/specification.py
fastclient/models/__init__.py
fastclient/models/http.py
fastclient/models/specification.py
fastclient/os/__init__.py
fastclient/os/files.py
fastclient/os/folders.py
fastclient/os/http.py
fastclient/parsers/__init__.py
fastclient/parsers/config.py
fastclient/parsers/specification.py
fastclient/utils/__init__.py
fastclient/utils/paths.py
fastclient/utils/strings.py
fastclient/utils/temp.py
fastclient/utils/urls.py
tests/__init__.py
tests/test_init.py
fastclientoas-0.0.1.dist-info/LICENSE
fastclientoas-0.0.1.dist-info/METADATA
fastclientoas-0.0.1.dist-info/WHEEL
fastclientoas-0.0.1.dist-info/entry_points.txt
fastclientoas-0.0.1.dist-info/top_level.txt
fastclientoas-0.0.1.dist-info/RECORD
